databricks/__init__.py
databricks/version.py
databricks/agents/__init__.py
databricks/agents/deployments.py
databricks/agents/feedback.py
databricks/agents/permissions.py
databricks/agents/reviews.py
databricks/agents/archive/__init__.py
databricks/agents/client/__init__.py
databricks/agents/client/rest_client.py
databricks/agents/datasets/__init__.py
databricks/agents/evals/__init__.py
databricks/agents/evals/datasets.py
databricks/agents/evals/judges.py
databricks/agents/evals/monitors.py
databricks/agents/monitoring/__init__.py
databricks/agents/review_app/__init__.py
databricks/agents/scorers/__init__.py
databricks/agents/sdk_utils/__init__.py
databricks/agents/sdk_utils/deployments.py
databricks/agents/sdk_utils/entities.py
databricks/agents/sdk_utils/permissions_checker.py
databricks/agents/telemetry/__init__.py
databricks/agents/utils/__init__.py
databricks/agents/utils/endpoint_utils.py
databricks/agents/utils/mlflow_utils.py
databricks/agents/utils/rest_utils.py
databricks/agents/utils/review_app_utils.py
databricks/agents/utils/uc.py
databricks/rag_eval/__init__.py
databricks/rag_eval/callable_builtin_judges.py
databricks/rag_eval/constants.py
databricks/rag_eval/context.py
databricks/rag_eval/custom_prompt_judge.py
databricks/rag_eval/entities.py
databricks/rag_eval/env_vars.py
databricks/rag_eval/evaluator_plugin.py
databricks/rag_eval/rest_entities.py
databricks/rag_eval/schemas.py
databricks/rag_eval/session.py
databricks/rag_eval/clients/__init__.py
databricks/rag_eval/clients/databricks_api_client.py
databricks/rag_eval/clients/mlflow_client.py
databricks/rag_eval/clients/managedevals/__init__.py
databricks/rag_eval/clients/managedevals/dataset_utils.py
databricks/rag_eval/clients/managedevals/managed_evals_client.py
databricks/rag_eval/clients/managedrag/__init__.py
databricks/rag_eval/clients/managedrag/managed_rag_client.py
databricks/rag_eval/clients/managedrag/proto_serde.py
databricks/rag_eval/config/__init__.py
databricks_agents-1.8.0.dist-info/METADATA
databricks_agents-1.8.0.dist-info/WHEEL
databricks_agents-1.8.0.dist-info/entry_points.txt
databricks_agents-1.8.0.dist-info/top_level.txt
databricks_agents-1.8.0.dist-info/RECORD
