Metadata-Version: 2.4
Name: databricks-agents
Version: 1.8.0
Summary: Mosaic AI Agent Framework SDK
Author: Databricks
Author-email: feedback@databricks.com
License: Databricks Proprietary License
Classifier: Development Status :: 3 - Alpha
Classifier: License :: Other/Proprietary License
Classifier: Programming Language :: Python :: Implementation :: CPython
Classifier: Programming Language :: Python :: Implementation :: PyPy
Requires-Python: >=3.10
Requires-Dist: databricks-connect
Requires-Dist: dataclasses-json
Requires-Dist: databricks-sdk[openai]>=0.58.0
Requires-Dist: jinja2>=3.0.0
Requires-Dist: mlflow-skinny<4.0.0,>=3.4.0
Requires-Dist: tenacity>=8.5
Requires-Dist: tiktoken>=0.8.0
Requires-Dist: tqdm
Requires-Dist: urllib3>=2.0
Requires-Dist: pydantic>=2
Requires-Dist: whenever==0.7.3
Requires-Dist: boto3>1
Requires-Dist: botocore
Requires-Dist: litellm==1.75.9
Dynamic: author
Dynamic: author-email
Dynamic: classifier
Dynamic: description
Dynamic: description-content-type
Dynamic: license
Dynamic: requires-dist
Dynamic: requires-python
Dynamic: summary
